viperx/__init__.py
viperx/config_engine.py
viperx/config_scanner.py
viperx/constants.py
viperx/content.py
viperx/core.py
viperx/dev_utils/__init__.py
viperx/dev_utils/release.py
viperx/licenses.py
viperx/main.py
viperx/migrations/__init__.py
viperx/migrations/v1_0_x.py
viperx/report.py
viperx/settings.py
viperx/templates/Base.ipynb.j2
viperx/templates/Base_General.ipynb.j2
viperx/templates/Base_Kaggle.ipynb.j2
viperx/templates/README.md.j2
viperx/templates/TEMPLATES.md
viperx/templates/__init__.py.j2
viperx/templates/config.py.j2
viperx/templates/config.yaml.j2
viperx/templates/data_loader.py.j2
viperx/templates/main.py.j2
viperx/templates/pyproject.toml.j2
viperx/templates/viperx_config.yaml.j2
viperx/templates.py
viperx/tests/conftest.py
viperx/tests/functional/test_builders.py
viperx/tests/functional/test_cli.py
viperx/tests/functional/test_education.py
viperx/tests/functional/test_file_content.py
viperx/tests/functional/test_licenses.py
viperx/tests/functional/test_project_types.py
viperx/tests/functional/test_templates.py
viperx/tests/functional/test_update_features.py
viperx/tests/integration/test_e2e.py
viperx/tests/scenarios/classic/test_custom.py
viperx/tests/scenarios/classic/test_defaults.py
viperx/tests/scenarios/test_edge_cases.py
viperx/tests/scenarios/test_package_commands.py
viperx/tests/scenarios/test_type_blocking.py
viperx/tests/scenarios/test_updates.py
viperx/tests/scenarios/workspace/test_overrides.py
viperx/tests/scenarios/workspace/test_structure.py
viperx/tests/unit/test_validation.py
viperx/utils.py
viperx-1.7.0.dist-info/WHEEL
viperx-1.7.0.dist-info/entry_points.txt
viperx-1.7.0.dist-info/METADATA
viperx-1.7.0.dist-info/RECORD
