Metadata-Version: 2.3
Name: viperx
Version: 1.7.0
Summary: The Mentor-Based Python Project Initializer. Learn best practices while building.
Keywords: python,project-template,uv,data-science,machine-learning
Author: Ivann KAMDEM
Author-email: Ivann KAMDEM <kapoivha@gmail.com>
License: MIT
Classifier: Development Status :: 4 - Beta
Classifier: Intended Audience :: Developers
Classifier: Topic :: Software Development :: Build Tools
Requires-Dist: gitpython>=3.1.46
Requires-Dist: jinja2>=3.1.6
Requires-Dist: rich>=14.2.0
Requires-Dist: typer>=0.21.1
Requires-Dist: pyyaml>=6.0.1
Requires-Dist: tomlkit>=0.13.2
Requires-Python: >=3.11
